mydash/__init__.py
mydash/client.py
mydash/widgets/__init__.py
mydash/widgets/bar_graph.py
mydash/widgets/base.py
mydash/widgets/custom.py
mydash/widgets/image.py
mydash/widgets/text.py
mydash-0.2.6.dist-info/METADATA
mydash-0.2.6.dist-info/WHEEL
mydash-0.2.6.dist-info/licenses/LICENSE
mydash-0.2.6.dist-info/RECORD
